setup.py
datx/__init__.py
datx/base_station.py
datx/city.py
datx/district.py
datx/util.py
ipip_datx.egg-info/PKG-INFO
ipip_datx.egg-info/SOURCES.txt
ipip_datx.egg-info/dependency_links.txt
ipip_datx.egg-info/top_level.txt