Metadata-Version: 1.1
Name: ipip-datx
Version: 0.3
Summary: IPIP.net官方支持维护的IP数据库datx格式解析代码库
Home-page: https://github.com/ipipdotnet/datx-python
Author: frk
Author-email: frk@ipip.net
License: Apache License Version 2.0
Platform: all
Classifier: Development Status :: 4 - Beta
Classifier: Operating System :: OS Independent
Classifier: Intended Audience :: Developers
Classifier: Programming Language :: Python
Classifier: Programming Language :: Python :: Implementation
Classifier: Programming Language :: Python :: 2
Classifier: Programming Language :: Python :: 2.7
Classifier: Programming Language :: Python :: 3
Classifier: Programming Language :: Python :: 3.4
Classifier: Programming Language :: Python :: 3.5
Classifier: Programming Language :: Python :: 3.6
Classifier: Topic :: Software Development :: Libraries
